starlingbankapi/__init__.py
starlingbankapi-3.3.dist-info/licenses/LICENSE
starlingbankapi-3.3.dist-info/METADATA
starlingbankapi-3.3.dist-info/WHEEL
starlingbankapi-3.3.dist-info/top_level.txt
starlingbankapi-3.3.dist-info/RECORD
