Metadata-Version: 2.4
Name: starlingbankapi
Version: 3.3
Summary: An unofficial Python package that provides access to parts of the Starling bank API. Designed to be used for personal use (i.e. using personal access tokens). Updated based on the 2019 codebase by Adam Dullage and the fork at https://github.com/rahulpdev/ to include Spaces support.
Home-page: https://github.com/richkershaw/starlingbankapi
Author: Rich Kershaw
Author-email: me@richkershaw.com
License: MIT
License-File: LICENSE
Requires-Dist: requests
Dynamic: author
Dynamic: author-email
Dynamic: home-page
Dynamic: license
Dynamic: license-file
Dynamic: requires-dist
Dynamic: summary
